FluxFramework/.gitattributes
FluxFramework/.gitignore
FluxFramework/FluxFramework.pyproj
FluxFramework/FluxFramework.sln
FluxFramework/LICENSE
FluxFramework/Menus.py
FluxFramework/Metadata.py
FluxFramework/README.md
FluxFramework/__init__.py
FluxFramework/main.py
FluxFramework/pyproject.toml
FluxFramework/update.bat
FluxFramework/version.txt
FluxFramework/.vs/FluxFramework/FileContentIndex/0ade867c-81a3-4d8b-9615-ab55a8cb5ed3.vsidx
FluxFramework/.vs/FluxFramework/FileContentIndex/2f27fd58-ec58-47cf-9074-f93bd6b1a63c.vsidx
FluxFramework/.vs/FluxFramework/FileContentIndex/35d99a1c-fa23-4d17-bfba-be88c99bbd88.vsidx
FluxFramework/.vs/FluxFramework/FileContentIndex/4e3db5e1-b844-4fa8-b9bb-3771ecc84b46.vsidx
FluxFramework/.vs/FluxFramework/FileContentIndex/read.lock
FluxFramework/.vs/FluxFramework/v17/.suo
FluxFramework/.vs/Framework/FileContentIndex/242c6c14-a42d-421e-a524-963c98b6b7d7.vsidx
FluxFramework/.vs/Framework/FileContentIndex/84ac4100-3552-4f53-982a-a3a599d41104.vsidx
FluxFramework/.vs/Framework/FileContentIndex/a6522078-dd6a-4c17-9e08-6330e18b6c78.vsidx
FluxFramework/.vs/Framework/FileContentIndex/f889b082-c50a-4b58-a048-b5824af30000.vsidx
FluxFramework/.vs/Framework/FileContentIndex/read.lock
FluxFramework/src/Metadata.py
FluxFramework/src/__init__.py
fluxframework-0.1.24.dist-info/METADATA
fluxframework-0.1.24.dist-info/WHEEL
fluxframework-0.1.24.dist-info/licenses/LICENSE
fluxframework-0.1.24.dist-info/RECORD
