Metadata-Version: 2.1
Name: FluxFramework
Version: 0.1.24
Summary: The core functionality of the FluxFramework
Project-URL: Homepage, https://github.com/DanielJacksonPortfolio/FluxFramework
Project-URL: Bug Tracker, https://github.com/DanielJacksonPortfolio/FluxFramework/issues
Author-email: Danny Jackson <danieljacksonportfolio@gmail.com>
License-File: LICENSE
Classifier: License :: OSI Approved :: MIT License
Classifier: Operating System :: OS Independent
Classifier: Programming Language :: Python :: 3
Requires-Python: >=3.7
